{
    "thread": {
        "uuid": "0a548b18f0019397d09cefe855f23cf41bf7144e",
        "url": "https://www.americanbankingnews.com/2025/01/10/brokerages-set-innodata-inc-nasdaqinod-pt-at-38-20.html",
        "site_full": "www.americanbankingnews.com",
        "site": "americanbankingnews.com",
        "site_section": "https://www.americanbankingnews.com",
        "site_categories": [
            "financial_news",
            "finance"
        ],
        "section_title": "American Banking and Market News",
        "title": "Brokerages Set Innodata Inc. (NASDAQ:INOD) PT at $38.20",
        "title_full": "Brokerages Set Innodata Inc. (NASDAQ:INOD) PT at $38.20",
        "published": "2025-01-10T07:14:00.000+02:00",
        "replies_count": 0,
        "participants_count": 1,
        "site_type": "news",
        "country": "US",
        "main_image": "",
        "performance_score": 0,
        "domain_rank": 138244,
        "domain_rank_updated": "2025-01-06T23:00:00.000+02:00",
        "social": {
            "facebook": {
                "likes": 0,
                "comments": 0,
                "shares": 0
            },
            "vk": {
                "shares": 0
            }
        }
    },
    "uuid": "0a548b18f0019397d09cefe855f23cf41bf7144e",
    "url": "https://www.americanbankingnews.com/2025/01/10/brokerages-set-innodata-inc-nasdaqinod-pt-at-38-20.html",
    "ord_in_thread": 0,
    "parent_url": null,
    "author": "ABMN Staff",
    "published": "2025-01-10T07:14:00.000+02:00",
    "title": "Brokerages Set Innodata Inc. (NASDAQ:INOD) PT at $38.20",
    "text": "Innodata Inc. ( NASDAQ:INOD – Get Free Report ) has received a consensus rating of “Buy” from the five research firms that are currently covering the firm, MarketBeat Ratings reports. Five investment analysts have rated the stock with a buy rating. The average 1 year target price among analysts that have issued a report on the stock in the last year is $38.20. A number of research analysts have issued reports on the stock. BWS Financial raised their price target on shares of Innodata from $30.00 to $45.00 and gave the stock a “buy” rating in a report on Friday, November 8th. Wedbush initiated coverage on Innodata in a research report on Thursday, December 19th. They set an “outperform” rating and a $48.00 price target for the company. Chardan Capital reissued a “buy” rating and issued a $45.00 price objective on shares of Innodata in a report on Friday, December 13th. StockNews.com upgraded Innodata from a “sell” rating to a “hold” rating in a research note on Saturday, November 16th. Finally, Craig Hallum started coverage on Innodata in a research report on Tuesday, September 17th. They issued a “buy” rating and a $23.00 target price on the stock. View Our Latest Stock Analysis on Innodata In other Innodata news, Director Louise C. Forlenza sold 4,000 shares of the stock in a transaction that occurred on Monday, November 25th. The stock was sold at an average price of $45.10, for a total transaction of $180,400.00. Following the transaction, the director now owns 8,278 shares in the company, valued at approximately $373,337.80. This represents a 32.58 % decrease in their ownership of the stock. The sale was disclosed in a document filed with the SEC, which can be accessed through this hyperlink . Also, Director Nauman Sabeeh Toor sold 110,207 shares of the business’s stock in a transaction that occurred on Friday, December 20th. The shares were sold at an average price of $44.00, for a total value of $4,849,108.00. Following the completion of the sale, the director now owns 209,194 shares of the company’s stock, valued at $9,204,536. This trade represents a 34.50 % decrease in their ownership of the stock. The disclosure for this sale can be found here . Insiders have sold 1,035,083 shares of company stock valued at $46,889,370 in the last 90 days. 15.23% of the stock is currently owned by company insiders. Large investors have recently added to or reduced their stakes in the stock. Geode Capital Management LLC increased its stake in shares of Innodata by 2.3% during the third quarter. Geode Capital Management LLC now owns 613,748 shares of the technology company’s stock worth $10,294,000 after purchasing an additional 13,609 shares in the last quarter. State Street Corp increased its stake in Innodata by 1.8% during the 3rd quarter. State Street Corp now owns 537,301 shares of the technology company’s stock worth $9,011,000 after buying an additional 9,408 shares in the last quarter. Deerfield Management Company L.P. Series C raised its holdings in shares of Innodata by 309.5% during the second quarter. Deerfield Management Company L.P. Series C now owns 111,814 shares of the technology company’s stock valued at $1,658,000 after acquiring an additional 84,509 shares during the last quarter. Marshall Wace LLP lifted its position in shares of Innodata by 83.9% in the second quarter. Marshall Wace LLP now owns 85,395 shares of the technology company’s stock valued at $1,266,000 after acquiring an additional 38,954 shares in the last quarter. Finally, Bank of New York Mellon Corp boosted its stake in shares of Innodata by 19.1% in the second quarter. Bank of New York Mellon Corp now owns 78,057 shares of the technology company’s stock worth $1,158,000 after acquiring an additional 12,515 shares during the last quarter. 30.75% of the stock is currently owned by institutional investors and hedge funds. Shares of INOD stock opened at $36.76 on Tuesday. Innodata has a fifty-two week low of $5.46 and a fifty-two week high of $55.17. The company has a debt-to-equity ratio of 0.15, a quick ratio of 1.84 and a current ratio of 1.84. The firm has a market capitalization of $1.07 billion, a price-to-earnings ratio of 62.31 and a beta of 2.59. The stock’s 50-day simple moving average is $39.35 and its 200-day simple moving average is $24.72. ( Get Free Report Innodata Inc operates as a global data engineering company in the United States, the United Kingdom, the Netherlands, Canada, and internationally. The company operates through three segments: Digital Data Solutions (DDS), Synodex, and Agility. The DDS segment engages in the provision of artificial intelligence (AI) data preparation services; collecting or creating training data; annotating training data; and training AI algorithms for its customers, as well as AI model deployment and integration services.",
    "highlightText": "",
    "highlightTitle": "",
    "highlightThreadTitle": "",
    "language": "english",
    "sentiment": "positive",
    "categories": [
        "Economy, Business and Finance"
    ],
    "topics": [
        "Economy, Business and Finance->financial and economic news",
        "Economy, Business and Finance->business reporting and performance",
        "Economy, Business and Finance->investment and opinion pieces"
    ],
    "ai_allow": true,
    "has_canonical": false,
    "breaking": null,
    "webz_reporter": false,
    "external_links": [
        "https://www.marketbeat.com/",
        "https://www.insidertrades.com/innodata-inc-stock/louise-c-forlenza/",
        "https://www.marketbeat.com/stocks/NASDAQ/INOD/",
        "https://www.marketbeat.com/stocks/NASDAQ/INOD/forecast/",
        "http://www.sec.gov/Archives/edgar/data/903651/000110465924131334/xslF345X05/tm2431872-1_4seq1.xml",
        "https://www.marketbeat.com/arnreports/ReportTickerOptin.aspx?RegistrationCode=TickerHyperlink&Prefix=NASDAQ&Symbol=INOD",
        "http://www.sec.gov/Archives/edgar/data/903651/000110465924123102/xslF345X05/tm2429608-1_4seq1.xml",
        "https://report.stocknews.com/sign-up/ticker/?ticker=INOD&lead_source=marketbeat_snra&utm_source=marketbeat_snra&utm_medium=article&utm_campaign=ticker&utm_term=INOD&utm_content=text_link",
        "https://marketbeat.com/arnreports/ReportTickerOptin.aspx?RegistrationCode=TickerHyperlink&Prefix=NASDAQ&Symbol=INOD",
        "http://sec.gov/Archives/edgar/data/903651/000110465924131334/xslF345X05/tm2431872-1_4seq1.xml",
        "https://marketbeat.com/stocks/NASDAQ/INOD/forecast/",
        "https://marketbeat.com/stocks/NASDAQ/INOD/",
        "https://www.marketbeat.com/stocks/NASDAQ/INOD/forecast",
        "https://insidertrades.com/innodata-inc-stock/louise-c-forlenza/",
        "https://www.marketbeat.com/arnreports/ReportTickerOptin.aspx",
        "https://www.marketbeat.com/stocks/NASDAQ/INOD",
        "https://www.marketbeat.com",
        "https://marketbeat.com/",
        "https://www.report.stocknews.com/sign-up/ticker/?ticker=INOD&lead_source=marketbeat_snra&utm_source=marketbeat_snra&utm_medium=article&utm_campaign=ticker&utm_term=INOD&utm_content=text_link",
        "https://www.insidertrades.com/innodata-inc-stock/louise-c-forlenza",
        "http://sec.gov/Archives/edgar/data/903651/000110465924123102/xslF345X05/tm2429608-1_4seq1.xml",
        "https://report.stocknews.com/sign-up/ticker/"
    ],
    "external_images": [],
    "entities": {
        "persons": [
            {
                "name": "Craig Hallum",
                "sentiment": "none"
            }
        ],
        "organizations": [
            {
                "name": "Brokerages Set Innodata Inc.",
                "sentiment": "none"
            },
            {
                "name": "MarketBeat Ratings",
                "sentiment": "none"
            }
        ],
        "locations": []
    },
    "syndication": {
        "syndicated": false,
        "syndicate_id": null,
        "first_syndicated": false
    },
    "rating": null,
    "crawled": "2025-01-10T08:55:35.252+02:00",
    "updated": "2025-01-10T08:55:35.252+02:00"
}