{
    "thread": {
        "uuid": "16eebb76ec3fc3dcb8e7ec97623a3e24bee3a94f",
        "url": "https://article.wn.com/view/2025/01/09/These_4_Solana_Alternatives_Could_Match_SOL_s_2021_Rally_and",
        "site_full": "article.wn.com",
        "site": "wn.com",
        "site_section": "https://wn.com/fiat-currencies",
        "site_categories": [
            "media"
        ],
        "section_title": "World News - FIAT Currencies",
        "title": "These 4 Solana Alternatives Could Match SOL's 2021 Rally and Turn $800 into $137,600 in 2025 - Worldnews.com",
        "title_full": "These 4 Solana Alternatives Could Match SOL's 2021 Rally and Turn $800 into $137,600 in 2025 - Worldnews.com",
        "published": "2025-01-09T02:00:00.000+02:00",
        "replies_count": 0,
        "participants_count": 0,
        "site_type": "news",
        "country": "US",
        "main_image": "",
        "performance_score": 0,
        "domain_rank": 3494,
        "domain_rank_updated": "2025-01-06T23:00:00.000+02:00",
        "social": {
            "facebook": {
                "likes": 0,
                "comments": 0,
                "shares": 0
            },
            "vk": {
                "shares": 0
            }
        }
    },
    "uuid": "16eebb76ec3fc3dcb8e7ec97623a3e24bee3a94f",
    "url": "https://article.wn.com/view/2025/01/09/These_4_Solana_Alternatives_Could_Match_SOL_s_2021_Rally_and",
    "ord_in_thread": 0,
    "parent_url": null,
    "author": null,
    "published": "2025-01-09T02:00:00.000+02:00",
    "title": "These 4 Solana Alternatives Could Match SOL's 2021 Rally and Turn $800 into $137,600 in 2025 - Worldnews.com",
    "text": "Four tokens have emerged as top contenders: Rexas Finance, Dogecoin, Uniswap, and Chainlink. Each shows the potential for significant investment growth. Let us delve deeper into these tokens and why they could be the reason to convert $800 into $137,600 in the subsequent year. Rexas Finance (RXS): The Tokenization Revolution",
    "highlightText": "",
    "highlightTitle": "",
    "highlightThreadTitle": "",
    "language": "english",
    "sentiment": "positive",
    "categories": [
        "Economy, Business and Finance",
        "Science and Technology",
        "Social Issue"
    ],
    "topics": [
        "Economy, Business and Finance->financial and economic news",
        "Economy, Business and Finance->investment and opinion pieces",
        "Science and Technology->economics",
        "Science and Technology->technology and engineering",
        "Social Issue->population and census",
        "Social Issue->social problem",
        "Social Issue->demographics"
    ],
    "ai_allow": true,
    "has_canonical": false,
    "breaking": null,
    "webz_reporter": false,
    "external_links": [],
    "external_images": [],
    "entities": {
        "persons": [],
        "organizations": [
            {
                "name": "Solana Alternatives Could Match SOL",
                "sentiment": "negative"
            }
        ],
        "locations": []
    },
    "syndication": {
        "syndicated": false,
        "syndicate_id": null,
        "first_syndicated": false
    },
    "rating": null,
    "crawled": "2025-01-10T02:57:11.211+02:00",
    "updated": "2025-01-10T02:57:11.211+02:00"
}