{
    "thread": {
        "uuid": "214b2affa744d6248716dc6e9a68989898abe8f2",
        "url": "https://economictimes.indiatimes.com/markets/stocks/news/these-large-and-mid-cap-stocks-can-give-more-than-25-return-in-1-year-according-to-analysts/articleshow/117110670.cms",
        "site_full": "economictimes.indiatimes.com",
        "site": "indiatimes.com",
        "site_section": "https://www.golf.einnews.com/live_feed",
        "site_categories": [
            "media",
            "top_news_nz",
            "top_news_au",
            "top_news_ae",
            "top_news_us",
            "top_news_gb",
            "top_news_th",
            "top_news_sa",
            "top_news_sg",
            "top_news_ph",
            "top_news_hk",
            "top_news_nl",
            "top_news_qa",
            "top_news_ie",
            "top_news_pk",
            "top_news_id",
            "top_news_dk",
            "top_news_eg",
            "top_news_za",
            "top_news_my",
            "top_news_kw",
            "top_news_be",
            "top_news_in",
            "top_news_ca",
            "top_news_iq",
            "top_news"
        ],
        "section_title": "Live Feed Wire - Golf News Today - EIN Presswire",
        "title": "These large- and mid-cap stocks can give more than 25% return in 1 year, according to analysts",
        "title_full": "These large- and mid-cap stocks can give more than 25% return in 1 year, according to analysts",
        "published": "2025-01-10T06:56:00.000+02:00",
        "replies_count": 0,
        "participants_count": 1,
        "site_type": "news",
        "country": "IN",
        "main_image": "https://img.etimg.com/thumb/msid-117110992,width-1070,height-580/premium-articleshow.jpg",
        "performance_score": 0,
        "domain_rank": 273,
        "domain_rank_updated": "2025-01-06T23:00:00.000+02:00",
        "social": {
            "facebook": {
                "likes": 0,
                "comments": 0,
                "shares": 0
            },
            "vk": {
                "shares": 0
            }
        }
    },
    "uuid": "214b2affa744d6248716dc6e9a68989898abe8f2",
    "url": "https://economictimes.indiatimes.com/markets/stocks/news/these-large-and-mid-cap-stocks-can-give-more-than-25-return-in-1-year-according-to-analysts/articleshow/117110670.cms",
    "ord_in_thread": 0,
    "parent_url": null,
    "author": "ETMarkets.com",
    "published": "2025-01-10T06:56:00.000+02:00",
    "title": "These large- and mid-cap stocks can give more than 25% return in 1 year, according to analysts",
    "text": "As the stock market goes through a phase of volatility, the street is again questioning whether valuations in major parts of the market are too high. And whether this correction will continue for some more time. If one looks at history, volatility in emerging markets is normally higher at this time of the year as the expectation of fund flows from the US and other countries gets readjusted. Now there is another aspect to volatility. If you are able to focus on the right stocks, it can be an opportunity for the long term.\nWorry not. You’re just a step away.\nExclusive Economic Times Stories, Editorials & Expert opinion across 20+ sectors\nStock analysis. Market Research. Industry Trends on 4000+ Stocks\nGet 1 Year Complimentary Subscription of TOI+ worth Rs.799/-",
    "highlightText": "",
    "highlightTitle": "",
    "highlightThreadTitle": "",
    "language": "english",
    "sentiment": "positive",
    "categories": [
        "Economy, Business and Finance"
    ],
    "topics": [
        "Economy, Business and Finance->financial and economic news",
        "Economy, Business and Finance->business and market analysis"
    ],
    "ai_allow": true,
    "has_canonical": true,
    "breaking": null,
    "webz_reporter": false,
    "external_links": [],
    "external_images": [],
    "entities": {
        "persons": [],
        "organizations": [],
        "locations": []
    },
    "syndication": {
        "syndicated": false,
        "syndicate_id": null,
        "first_syndicated": false
    },
    "rating": null,
    "crawled": "2025-01-10T09:50:29.713+02:00",
    "updated": "2025-01-10T09:50:29.713+02:00"
}