{
    "thread": {
        "uuid": "aa098b4b2122608b1bc08c80e334bab95a513393",
        "url": "https://www.newsbreak.com/afrotech-1696378/3752860383086-2025-workforce-trends-show-that-landing-your-dream-career-may-be-more-obtainable-than-you-think",
        "site_full": "www.newsbreak.com",
        "site": "newsbreak.com",
        "site_section": "https://www.newsbreak.com/afrotech-1696378",
        "site_categories": [
            "under_construction"
        ],
        "section_title": "Afrotech&#x27;s Home Page | NewsBreak",
        "title": "2025 Workforce Trends Show That Landing Your Dream Career May Be More Obtainable Than You Think - NewsBreak",
        "title_full": "2025 Workforce Trends Show That Landing Your Dream Career May Be More Obtainable Than You Think - NewsBreak",
        "published": "2025-01-09T23:35:00.000+02:00",
        "replies_count": 0,
        "participants_count": 1,
        "site_type": "news",
        "country": "US",
        "main_image": "https://img.particlenews.com/img/id/1khBTf_0y1T3vRx00",
        "performance_score": 0,
        "domain_rank": 3611,
        "domain_rank_updated": "2025-01-06T23:00:00.000+02:00",
        "social": {
            "facebook": {
                "likes": 0,
                "comments": 0,
                "shares": 0
            },
            "vk": {
                "shares": 0
            }
        }
    },
    "uuid": "aa098b4b2122608b1bc08c80e334bab95a513393",
    "url": "https://www.newsbreak.com/afrotech-1696378/3752860383086-2025-workforce-trends-show-that-landing-your-dream-career-may-be-more-obtainable-than-you-think",
    "ord_in_thread": 0,
    "parent_url": null,
    "author": "Josh Rodgers",
    "published": "2025-01-09T23:35:00.000+02:00",
    "title": "2025 Workforce Trends Show That Landing Your Dream Career May Be More Obtainable Than You Think - NewsBreak",
    "text": "By Josh Rodgers ,\n12 hours ago\nIf the workforce were a playlist, 2025 would give “Renaissance” by Beyoncé — a vibe shift, a reset, and a clear signal that the world of work is hitting some new high notes. The game is changing, and whether it’s artificial intelligence (AI) running point, the return of curated travel experiences, or frontline roles making a comeback, one thing is clear: opportunities are out here, but they won’t fall into your lap.\nFor Black professionals, the stakes are high. Job competition is fierce, with 2.5 applicants per role compared to 1.5 in 2022. Confidence is shaky, and hiring managers ghost candidates like they forgot the assignment. However, according to LinkedIn’s Jobs on the Rise 2025 report , nearly 60% of these roles are fresh on the scene, signaling change and opportunity.\n“Fields like AI, experiential industries, and frontline jobs are booming, offering fresh opportunities to break into spaces where we’ve historically been underrepresented,” says Andrew McCaskill.\nAI: The Blueprint is Digital, But the Moves Are Human AI isn’t coming — it’s here. And it’s not just changing tech; it’s changing everything. Roles like Artificial Intelligence Engineer, AI Consultant, and AI Researcher are climbing the charts in Silicon Valley and across industries like healthcare, finance, and education.\nBased on data from Statia, the U.S. AI market has ballooned by nearly $50 billion since 2023, and it’s still growing. But here’s the kicker: breaking into AI isn’t just about knowing Python or building models — it’s about blending technical chops with soft skills that hit differently.\n“AI skills can get you in the door, but your soft skills—communication, leadership, and adaptability—will get you noticed, promoted, and (potentially) better PAID,” McCaskill points out.\nSo yes, get the AI certifications, learn machine learning, and understand cloud computing. But also learn how to command a room, lead a team, and advocate for yourself. Because let’s keep it real, AI might write the code but can’t write your legacy.\nTravel & Live Experiences: Back Outside Energy After a long stretch of Zoom fatigue and virtual everything, people are back outside and doing it big. Travel isn’t just about vacations anymore, it’s about curated experiences, intentional connections, and, yes, flex-worthy Instagram moments.\nRoles like Travel Advisor and Event Coordinator are thriving because people are willing to invest in experiences that feel personal, luxurious, and culturally resonant. And guess what? Black professionals are uniquely positioned to lead in this space.\n“There isn’t an AI model trained on Black joy or Black experiences,” McCaskill reminds us.\nBlack travelers represent a projected buying power of $1.8 trillion by the end of 2024. That’s not small money, it’s generational influence. If you’re considering getting into these industries, don’t just clock in — own your space.\n“We’re not just booking trips or planning events. We can offer a level of care, culture, and connection that tech can’t replicate,” McCaskill says.\nBuild your brand, share your expertise on platforms like LinkedIn, and ensure that people know your name when planning their next big moment.\nFrontline Roles: Chess, Not Checkers Frontline jobs like Security Guard and Research Librarian are back in the spotlight, and they’re not just stopgaps — they’re strategic moves. These roles are recession-proof and essential, and for many, they’re the first step in a much bigger journey.\n“Think of it as playing chess, not checkers. Build transferable skills, network internally, and use these roles as vehicles — not destinations,” McCaskill advises.\nHere’s the playbook:\nBuild skills like communication, problem-solving, and leadership. Treat every day like it’s an audition for your next role. Get curious—understand how the business makes money, where the growth is happening, and where you can fit into the bigger picture. Companies are prioritizing internal hires, which means the person working security today could be running operations tomorrow. But only if you play it smart.\nNetworks & Mentorship: Who’s In Your Corner? Networking isn’t about who you know, it’s about who knows you and what they say when you’re not in the room.\nAnd let’s be honest: too many of us underestimate the power of our networks. According to LinkedIn data, while 80% of Black and Latino professionals know networks matter, fewer than 25% have used theirs to land a role.\n“Networking isn’t about collecting business cards—it’s about building genuine relationships and making sure your network knows how to advocate for you,” says McCaskill.\nLinkedIn isn’t just a digital résumé; it’s a resource. Use the My Network tab to stay connected, follow leaders in your field, and share your wins. People can’t root for you if they don’t know what game you’re playing.\nYour 2025 Career Playbook The future of work isn’t waiting for anyone — it’s here. And while the competition is steep, the opportunity is real. Success in 2025 isn’t about having all the answers, it’s about asking the right questions and staying ready.\nHere’s the cheat code:\nAssess and Prepare: Take stock of your strengths and know where you want to grow. Update Your LinkedIn Profile: Your digital handshake needs to match your ambition. Network with Purpose: Relationships are currency. Spend wisely. Play the Long Game: Be strategic, stay adaptable, and remember, every move counts. Or, as McCaskill puts it: “Despite the challenges, opportunity is still out there, and we always persevere. The key is to work smarter, not harder.”\nThe workforce of 2025 is a remix of resilience, adaptability, and cultural influence. And for Black professionals, the moment isn’t coming—it’s already here. Whether AI, travel, frontline roles, or leadership, the key is to show up ready, make your presence felt, and claim your seat at every table you enter.\nBecause in this game, the most prepared aren’t just surviving — they’re thriving.\nThe post 2025 Workforce Trends Show That Landing Your Dream Career May Be More Obtainable Than You Think appeared first on AfroTech .\nThe post 2025 Workforce Trends Show That Landing Your Dream Career May Be More Obtainable Than You Think appeared first on AfroTech .\n2",
    "highlightText": "",
    "highlightTitle": "",
    "highlightThreadTitle": "",
    "language": "english",
    "sentiment": "positive",
    "categories": [
        "Economy, Business and Finance",
        "Education",
        "Social Issue"
    ],
    "topics": [
        "Economy, Business and Finance->business strategy and marketing",
        "Economy, Business and Finance->human resources",
        "Economy, Business and Finance->financial and economic news",
        "Education->vocational education",
        "Social Issue->social condition",
        "Social Issue->demographics"
    ],
    "ai_allow": true,
    "has_canonical": false,
    "breaking": null,
    "webz_reporter": false,
    "external_links": [
        "https://afrotech.com/zoom-better-lays-off-thousands-employees",
        "https://afrotech.com/four-ways-to-become-recession-proof",
        "https://afrotech.com/afrotech-24-increase-divine-wisdom-nigeria-hackathon",
        "https://afrotech.com/best-hashtags-for-business-networking",
        "https://afrotech.com/btgm-jame-jackson",
        "https://cms.afrotech.com",
        "https://afrotech.com",
        "https://afrotech.com/2025-career-trends",
        "https://www.globenewswire.com/news-release/2024/12/11/2995486/0/en/Founder-Group-Enters-the-US-180-Billion-AI-Market-With-AI-Powered-Drone-Technology-for-Solar-Farm-Inspections.html#:~:text=According%20to%20Statista%2C%20the%20global,US%24800%20billion%20by%202030.",
        "https://img.particlenews.com/image.php?url=1khBTf_0y1T3vRx00",
        "https://www.linkedin.com/pulse/linkedin-jobs-rise-2025-25-fastest-growing-us-linkedin-news-gryie/",
        "https://img.particlenews.com/image.php?type=thumbnail_580x000&url=1khBTf_0y1T3vRx00",
        "https://www.afrotech.com/zoom-better-lays-off-thousands-employees",
        "https://www.afrotech.com/btgm-jame-jackson",
        "https://www.afrotech.com/2025-career-trends",
        "https://www.cms.afrotech.com",
        "https://www.linkedin.com/pulse/linkedin-jobs-rise-2025-25-fastest-growing-us-linkedin-news-gryie",
        "https://www.img.particlenews.com/image.php?type=thumbnail_580x000&url=1khBTf_0y1T3vRx00",
        "https://www.afrotech.com/best-hashtags-for-business-networking",
        "https://www.img.particlenews.com/image.php?url=1khBTf_0y1T3vRx00",
        "https://img.particlenews.com/image.php",
        "https://globenewswire.com/news-release/2024/12/11/2995486/0/en/Founder-Group-Enters-the-US-180-Billion-AI-Market-With-AI-Powered-Drone-Technology-for-Solar-Farm-Inspections.html#:~:text=According%20to%20Statista%2C%20the%20global,US%24800%20billion%20by%202030.",
        "https://www.afrotech.com/afrotech-24-increase-divine-wisdom-nigeria-hackathon",
        "https://www.afrotech.com",
        "https://www.afrotech.com/four-ways-to-become-recession-proof",
        "https://linkedin.com/pulse/linkedin-jobs-rise-2025-25-fastest-growing-us-linkedin-news-gryie/"
    ],
    "external_images": [],
    "entities": {
        "persons": [
            {
                "name": "Josh Rodgers",
                "sentiment": "negative"
            },
            {
                "name": "Andrew McCaskill",
                "sentiment": "none"
            }
        ],
        "organizations": [],
        "locations": []
    },
    "syndication": {
        "syndicated": false,
        "syndicate_id": null,
        "first_syndicated": false
    },
    "rating": null,
    "crawled": "2025-01-10T06:49:57.181+02:00",
    "updated": "2025-01-10T06:49:57.181+02:00"
}