{
    "thread": {
        "uuid": "9aa33f846739c417deab8762ac0d9cc5aaca6b79",
        "url": "https://www.channelnewsasia.com/business/tsmcs-fourth-quarter-revenue-handily-beats-market-forecast-4849561",
        "site_full": "www.channelnewsasia.com",
        "site": "channelnewsasia.com",
        "site_section": "https://channelnewsasia.com/cna-homepage-singapore?web_topstories-navbar_internal_10012022_cna=",
        "site_categories": [
            "society",
            "tech",
            "top_news_ph",
            "top_news_th",
            "top_news_id",
            "top_news_sg",
            "top_news_my",
            "top_news"
        ],
        "section_title": "Breaking News and Analysis on Asia and the World | Real-Time Coverage out of Asia and Singapore - CNA",
        "title": "TSMC's fourth-quarter revenue handily beats market forecast - CNA",
        "title_full": "TSMC's fourth-quarter revenue handily beats market forecast - CNA",
        "published": "2025-01-10T07:39:00.000+02:00",
        "replies_count": 0,
        "participants_count": 1,
        "site_type": "news",
        "country": "SG",
        "main_image": "https://dam.mediacorp.sg/image/upload/s--rKJGrT5c--/fl_relative,g_south_east,l_mediacorp:cna:watermark:2024-04:reuters_1,w_0.1/f_auto,q_auto/c_fill,g_auto,h_676,w_1200/v1/one-cms/core/2025-01-10t053918z_1_lynxmpel0904l_rtroptp_3_taiwan-tsmc.jpg?itok=wl1r9AXG",
        "performance_score": 0,
        "domain_rank": 1639,
        "domain_rank_updated": "2025-01-06T23:00:00.000+02:00",
        "social": {
            "facebook": {
                "likes": 0,
                "comments": 0,
                "shares": 0
            },
            "vk": {
                "shares": 0
            }
        }
    },
    "uuid": "9aa33f846739c417deab8762ac0d9cc5aaca6b79",
    "url": "https://www.channelnewsasia.com/business/tsmcs-fourth-quarter-revenue-handily-beats-market-forecast-4849561",
    "ord_in_thread": 0,
    "parent_url": null,
    "author": "CNA",
    "published": "2025-01-10T07:39:00.000+02:00",
    "title": "TSMC's fourth-quarter revenue handily beats market forecast - CNA",
    "text": "Advertisement Business\nTSMC's fourth-quarter revenue handily beats market forecast\nFILE PHOTO: People walk across the streets in front of TSMC Fab 18 at Southern Taiwan Science Park in Tainan, Taiwan December 5, 2024. REUTERS/Ann Wang/ File Photo\n10 Jan 2025 01:39PM Bookmark Bookmark Share WhatsApp Telegram Facebook Twitter Email LinkedIn Read a summary of this article on FAST. Get bite-sized news via a new\ncards interface. Give it a try. Click here to return to FAST Tap here to return to FAST FAST TAIPEI : TSMC, the world's largest contract chipmaker, on Friday reported fourth-quarter revenue of T$868.42 billion ($26.36 billion), according to Reuters calculations, easily beating a market forecast, as the company reaps the benefit from artificial intelligence demand.\nAn LSEG SmartEstimate, drawn from 23 analysts, had predicted fourth-quarter revenue of T$853.57 billion.\nTaiwan Semiconductor Manufacturing Co (TSMC) is a major supplier to companies including Apple and Nvidia.\n($1 = 32.9530 Taiwan dollars)\nSource: Reuters Sign up for our newsletters Get our pick of top stories and thought-provoking articles in your inbox\nSubscribe here Get the CNA app Stay updated with notifications for breaking news and our best stories\nDownload here Get WhatsApp alerts\nJoin our channel for the top reads for the day on your preferred chat app\nJoin here Advertisement Also worth reading Content is loading... Advertisement Expand to read the full story Get bite-sized news via a new\ncards interface. Give it a try. Click here to return to FAST Tap here to return to FAST FAST",
    "highlightText": "",
    "highlightTitle": "",
    "highlightThreadTitle": "",
    "language": "english",
    "sentiment": "positive",
    "categories": [
        "Economy, Business and Finance"
    ],
    "topics": [
        "Economy, Business and Finance->business reporting and performance",
        "Economy, Business and Finance->financial and economic news"
    ],
    "ai_allow": true,
    "has_canonical": false,
    "breaking": null,
    "webz_reporter": false,
    "external_links": [
        "https://cna.asia/whatsapp",
        "https://www.cna.asia/whatsapp"
    ],
    "external_images": [],
    "entities": {
        "persons": [],
        "organizations": [],
        "locations": []
    },
    "syndication": {
        "syndicated": false,
        "syndicate_id": null,
        "first_syndicated": false
    },
    "rating": null,
    "crawled": "2025-01-10T08:32:07.290+02:00",
    "updated": "2025-01-10T09:34:11.240+02:00"
}